sessionz/__init__.py
sessionz/core.py
sessionz/log.py
sessionz/server.py
sessionz-0.1.1.dist-info/METADATA
sessionz-0.1.1.dist-info/WHEEL
sessionz-0.1.1.dist-info/top_level.txt
sessionz-0.1.1.dist-info/RECORD
