Metadata-Version: 2.4
Name: sessionz
Version: 0.1.1
Summary: Add your description here
Requires-Python: >=3.13
Requires-Dist: toml==0.10.2
